udata_search_service/__init__.py
udata_search_service/app.py
udata_search_service/config.py
udata_search_service/container.py
udata_search_service/wsgi.py
udata_search_service/domain/__init__.py
udata_search_service/domain/entities.py
udata_search_service/domain/factories.py
udata_search_service/domain/interfaces.py
udata_search_service/infrastructure/__init__.py
udata_search_service/infrastructure/consumers.py
udata_search_service/infrastructure/migrate.py
udata_search_service/infrastructure/search_clients.py
udata_search_service/infrastructure/services.py
udata_search_service/infrastructure/utils.py
udata_search_service/presentation/__init__.py
udata_search_service/presentation/api.py
udata_search_service/presentation/commands.py
udata_search_service/presentation/utils.py
udata_search_service-2.3.3.dist-info/entry_points.txt
udata_search_service-2.3.3.dist-info/WHEEL
udata_search_service-2.3.3.dist-info/METADATA
udata_search_service-2.3.3.dist-info/RECORD
