Metadata-Version: 2.4
Name: udata-search-service
Version: 2.3.3
Summary: udata search service
Author-email: Opendata Team <opendatateam@data.gouv.fr>
Requires-Dist: dependency-injector==4.48.1
Requires-Dist: elasticsearch==8.19.0
Requires-Dist: elasticsearch_dsl==8.18.0
Requires-Dist: factory-boy==3.3.3
Requires-Dist: Faker==37.5.3
Requires-Dist: Flask==3.1.2
Requires-Dist: pydantic==2.11.7
Requires-Dist: markdown==3.8.2
Requires-Dist: beautifulsoup4==4.13.5
Requires-Dist: werkzeug==3.1.5
Requires-Dist: flake8==7.3.0 ; extra == "dev"
Requires-Dist: flit==3.12.0 ; extra == "dev"
Requires-Dist: gunicorn==23.0.0 ; extra == "dev"
Requires-Dist: pytest==8.4.1 ; extra == "dev"
Requires-Dist: pytest-flask==1.3.0 ; extra == "dev"
Project-URL: Home, https://github.com/opendatateam/udata-search-service
Provides-Extra: dev
